MANIFEST.in
README.md
requirements.txt
setup.cfg
setup.py
lightning/__init__.py
lightning/main.py
lightning/session.py
lightning/visualization.py
lightning/lib/__init__.py
lightning/lib/embed.js
lightning/lib/icon.png
lightning/lib/template.html
lightning/types/__init__.py
lightning/types/base.py
lightning/types/decorators.py
lightning/types/images.py
lightning/types/plots.py
lightning/types/streaming.py
lightning/types/three.py
lightning/types/utils.py
lightning_python.egg-info/PKG-INFO
lightning_python.egg-info/SOURCES.txt
lightning_python.egg-info/dependency_links.txt
lightning_python.egg-info/requires.txt
lightning_python.egg-info/top_level.txt
test/test_client.py
test/test_images.py
test/test_plots.py