Metadata-Version: 1.0
Name: lightning-python
Version: 1.1.1
Summary: A Python client library for the Lightning data visualization server
Home-page: https://github.com/lightning-viz/lightning-python
Author: Matthew Conlen
Author-email: github@mathisonian.com
License: MIT
Keywords: lightning data data-viz
Platform: UNKNOWN
